{"lang": "es", "user": {"profile_sidebar_fill_color": "DDEEF6", "following": false, "profile_banner_url": "https://pbs.twimg.com/profile_banners/2848881309/1448936432", "screen_name": "noeliachok", "geo_enabled": true, "lang": "es", "friends_count": 750, "id_str": "2848881309", "profile_link_color": "1DA1F2", "has_extended_profile": false, "id": 2848881309, "profile_background_tile": false, "entities": {"description": {"urls": []}}, "description": "...", "is_translation_enabled": false, "time_zone": null, "default_profile": true, "profile_image_url_https": "https://pbs.twimg.com/profile_images/671514169397637120/iKVmwlS0_normal.jpg", "follow_request_sent": false, "default_profile_image": false, "profile_background_image_url": "http://abs.twimg.com/images/themes/theme1/bg.png", "listed_count": 1, "profile_sidebar_border_color": "C0DEED", "name": "Snuff", "followers_count": 188, "url": null, "is_translator": false, "utc_offset": null, "protected": false, "statuses_count": 1018, "created_at": "Tue Oct 28 22:05:54 +0000 2014", "profile_image_url": "http://pbs.twimg.com/profile_images/671514169397637120/iKVmwlS0_normal.jpg", "verified": false, "profile_use_background_image": true, "location": "", "notifications": false, "favourites_count": 212, "profile_background_image_url_https": "https://abs.twimg.com/images/themes/theme1/bg.png", "profile_text_color": "333333", "profile_background_color": "C0DEED", "contributors_enabled": false, "translator_type": "none"}, "id_str": "603579849760964608", "truncated": false, "id": 603579849760964608, "favorite_count": 0, "entities": {"user_mentions": [], "urls": [], "hashtags": [{"indices": [32, 41], "text": "Sarcasmo"}], "symbols": []}, "retweet_count": 0, "in_reply_to_user_id": null, "place": {"attributes": {}, "name": "Ciudad del Libertador General San Mart\u00edn", "country_code": "AR", "url": "https://api.twitter.com/1.1/geo/id/004b853c78703c20.json", "country": "Argentina", "full_name": "Ciudad del Libertador General San Mart\u00edn, Argentina", "bounding_box": {"coordinates": [[[-58.618436, -34.5974062], [-58.509913, -34.5974062], [-58.509913, -34.491912], [-58.618436, -34.491912]]], "type": "Polygon"}, "id": "004b853c78703c20", "contained_within": [], "place_type": "city"}, "geo": null, "coordinates": null, "in_reply_to_screen_name": null, "retweeted": false, "is_quote_status": false, "text": "Definitivamente toda una \"Dama\" #Sarcasmo", "in_reply_to_status_id": null, "source": "<a href=\"http://twitter.com/download/android\" rel=\"nofollow\">Twitter for Android</a>", "contributors": null, "in_reply_to_status_id_str": null, "created_at": "Wed May 27 15:13:44 +0000 2015", "favorited": false, "in_reply_to_user_id_str": null}