{"source": "<a href=\"http://twitter.com/download/android\" rel=\"nofollow\">Twitter for Android</a>", "created_at": "Thu Jun 11 17:05:36 +0000 2015", "lang": "es", "is_quote_status": false, "text": "#Soyaficionadoalostoros y a los colados en transmilenio y a los robos en mi ciudad que buena vida llevamos #Sarcasmo", "in_reply_to_status_id": null, "entities": {"symbols": [], "hashtags": [{"indices": [0, 23], "text": "Soyaficionadoalostoros"}, {"indices": [107, 116], "text": "Sarcasmo"}], "user_mentions": [], "urls": []}, "truncated": false, "favorited": false, "user": {"favourites_count": 1441, "created_at": "Tue Jul 06 16:58:52 +0000 2010", "lang": "es", "protected": false, "listed_count": 5, "profile_image_url_https": "https://pbs.twimg.com/profile_images/795452948335755264/R1gIjWLH_normal.jpg", "profile_background_image_url": "http://abs.twimg.com/images/themes/theme14/bg.gif", "entities": {"description": {"urls": []}}, "follow_request_sent": false, "default_profile_image": false, "notifications": false, "friends_count": 654, "location": "Bogota Colombia", "id_str": "163526551", "utc_offset": null, "profile_image_url": "http://pbs.twimg.com/profile_images/795452948335755264/R1gIjWLH_normal.jpg", "has_extended_profile": true, "screen_name": "caballerohernan", "id": 163526551, "followers_count": 718, "time_zone": null, "profile_sidebar_border_color": "FFFFFF", "description": "Soledad amiga he decidido tenerte en mi vida ya que de malas compa\u00f1\u00edas he vivido\nThe Big bang theory \nThe Walking dead \nGames of Thrones \n\n\nsnap Hernan_caballer", "statuses_count": 5219, "name": "PuraMierda \ud83c\udfb8", "profile_background_color": "131516", "geo_enabled": true, "profile_banner_url": "https://pbs.twimg.com/profile_banners/163526551/1462468364", "contributors_enabled": false, "profile_sidebar_fill_color": "EFEFEF", "default_profile": false, "verified": false, "profile_background_image_url_https": "https://abs.twimg.com/images/themes/theme14/bg.gif", "profile_use_background_image": true, "is_translation_enabled": false, "is_translator": false, "following": false, "profile_link_color": "009999", "translator_type": "none", "url": null, "profile_background_tile": true, "profile_text_color": "333333"}, "retweeted": false, "in_reply_to_user_id": null, "id": 609043818881630208, "retweet_count": 0, "geo": null, "contributors": null, "in_reply_to_status_id_str": null, "id_str": "609043818881630208", "in_reply_to_screen_name": null, "coordinates": null, "in_reply_to_user_id_str": null, "favorite_count": 0, "place": null}