{"source": "<a href=\"http://twitter.com/download/android\" rel=\"nofollow\">Twitter for Android</a>", "created_at": "Thu Jun 18 15:06:28 +0000 2015", "lang": "es", "is_quote_status": false, "text": "Que suerte tengo :)))))))) #Ironia", "in_reply_to_status_id": null, "entities": {"symbols": [], "hashtags": [{"indices": [27, 34], "text": "Ironia"}], "user_mentions": [], "urls": []}, "truncated": false, "favorited": false, "user": {"favourites_count": 6403, "created_at": "Sat Mar 30 12:32:40 +0000 2013", "lang": "es", "protected": false, "listed_count": 1, "profile_image_url_https": "https://pbs.twimg.com/profile_images/833271191699877889/4W2hTU4Q_normal.jpg", "profile_background_image_url": "http://abs.twimg.com/images/themes/theme1/bg.png", "entities": {"description": {"urls": []}, "url": {"urls": [{"expanded_url": "http://aprendiendoasentir.blogspot.es", "indices": [0, 23], "url": "https://t.co/JEtQAgd9pF", "display_url": "aprendiendoasentir.blogspot.es"}]}}, "follow_request_sent": false, "default_profile_image": false, "notifications": false, "friends_count": 386, "location": "Hu\u00e9scar (GRANADA) ", "id_str": "1316363084", "utc_offset": null, "profile_image_url": "http://pbs.twimg.com/profile_images/833271191699877889/4W2hTU4Q_normal.jpg", "has_extended_profile": true, "screen_name": "Raquelillamr99", "id": 1316363084, "followers_count": 611, "time_zone": null, "profile_sidebar_border_color": "FFFFFF", "description": "Poeta a ratos //La vida sin rock no es vida (y sin gatos tampoco)\n\n\n\n\n\n\n\n\n\n\n\n\n\n\n\n\n\n\n\n\n\n\n\n\n\n\n\n\n\n\n\n\n\n\n\n\n\n\n\n\n\n\n\n\n\n\n\n\n\n\n\n\n\n\n\n\n\n\n\n\n\n\n\n\n\n\n\n\n\n\n\n\n\n\nTrabajo social UGR\ud83c\udf93", "statuses_count": 9112, "name": "Raquel", "profile_background_color": "C0DEED", "geo_enabled": true, "profile_banner_url": "https://pbs.twimg.com/profile_banners/1316363084/1469734112", "contributors_enabled": false, "profile_sidebar_fill_color": "DDEEF6", "default_profile": false, "verified": false, "profile_background_image_url_https": "https://abs.twimg.com/images/themes/theme1/bg.png", "profile_use_background_image": true, "is_translation_enabled": false, "is_translator": false, "following": false, "profile_link_color": "0084B4", "translator_type": "none", "url": "https://t.co/JEtQAgd9pF", "profile_background_tile": true, "profile_text_color": "333333"}, "retweeted": false, "in_reply_to_user_id": null, "id": 611550553185906689, "retweet_count": 0, "geo": null, "contributors": null, "in_reply_to_status_id_str": null, "id_str": "611550553185906689", "in_reply_to_screen_name": null, "coordinates": null, "in_reply_to_user_id_str": null, "favorite_count": 0, "place": null}