{"source": "<a href=\"http://twitter.com/download/iphone\" rel=\"nofollow\">Twitter for iPhone</a>", "created_at": "Mon Jun 22 03:58:08 +0000 2015", "lang": "es", "is_quote_status": false, "text": "@ApartaSoyMedico Que gracioso eres #ironia.", "in_reply_to_status_id": 612831575496126464, "entities": {"symbols": [], "hashtags": [{"indices": [35, 42], "text": "ironia"}], "user_mentions": [{"id_str": "2879673303", "screen_name": "ApartaSoyMedico", "name": "Ex @PabloHostiaPuta", "indices": [0, 16], "id": 2879673303}], "urls": []}, "truncated": false, "favorited": false, "user": {"favourites_count": 21239, "created_at": "Tue May 08 15:18:05 +0000 2012", "lang": "es", "protected": false, "listed_count": 25, "profile_image_url_https": "https://pbs.twimg.com/profile_images/1008613585692577792/Y1MlP_BC_normal.jpg", "profile_background_image_url": "http://abs.twimg.com/images/themes/theme1/bg.png", "entities": {"description": {"urls": []}, "url": {"urls": [{"expanded_url": "https://www.instagram.com/lironzuela/", "indices": [0, 23], "url": "https://t.co/1k5AhQAmGW", "display_url": "instagram.com/lironzuela/"}]}}, "follow_request_sent": false, "default_profile_image": false, "notifications": false, "friends_count": 754, "location": "Pontevedra.", "id_str": "574556758", "utc_offset": null, "profile_image_url": "http://pbs.twimg.com/profile_images/1008613585692577792/Y1MlP_BC_normal.jpg", "has_extended_profile": true, "screen_name": "BocadillodeToxo", "id": 574556758, "followers_count": 825, "time_zone": null, "profile_sidebar_border_color": "FFFFFF", "description": "Ten cuidado, qui\u00e9n ha sido destruido sabe destruir//Muy fan de Tim Burton, los purrus en la barriga, los gatitos y las cabras// Extremoduro\u200b//Cecilia", "statuses_count": 31010, "name": "Mrs. Black", "profile_background_color": "0099B9", "geo_enabled": true, "profile_banner_url": "https://pbs.twimg.com/profile_banners/574556758/1451873349", "contributors_enabled": false, "profile_sidebar_fill_color": "DDEEF6", "default_profile": false, "verified": false, "profile_background_image_url_https": "https://abs.twimg.com/images/themes/theme1/bg.png", "profile_use_background_image": true, "is_translation_enabled": false, "is_translator": false, "following": false, "profile_link_color": "F58EA8", "translator_type": "none", "url": "https://t.co/1k5AhQAmGW", "profile_background_tile": true, "profile_text_color": "333333"}, "retweeted": false, "in_reply_to_user_id": 2879673303, "id": 612831914194567169, "retweet_count": 0, "geo": null, "contributors": null, "in_reply_to_status_id_str": "612831575496126464", "id_str": "612831914194567169", "in_reply_to_screen_name": "ApartaSoyMedico", "coordinates": null, "in_reply_to_user_id_str": "2879673303", "favorite_count": 0, "place": null}