{"lang": "es", "user": {"profile_sidebar_fill_color": "99CC33", "following": false, "profile_banner_url": "https://pbs.twimg.com/profile_banners/166481343/1467813875", "screen_name": "gmblanca", "geo_enabled": true, "lang": "es", "friends_count": 334, "id_str": "166481343", "profile_link_color": "D02B55", "has_extended_profile": true, "id": 166481343, "profile_background_tile": false, "entities": {"description": {"urls": []}}, "description": "Del 1996.                                  Instagram: @blancagm2", "is_translation_enabled": false, "time_zone": null, "default_profile": false, "profile_image_url_https": "https://pbs.twimg.com/profile_images/750691598204272640/JQzPIF_I_normal.jpg", "follow_request_sent": false, "default_profile_image": false, "profile_background_image_url": "http://abs.twimg.com/images/themes/theme5/bg.gif", "listed_count": 0, "profile_sidebar_border_color": "829D5E", "name": "Blanca Garc\u00eda", "followers_count": 327, "url": null, "is_translator": false, "utc_offset": null, "protected": false, "statuses_count": 4507, "created_at": "Wed Jul 14 07:29:39 +0000 2010", "profile_image_url": "http://pbs.twimg.com/profile_images/750691598204272640/JQzPIF_I_normal.jpg", "verified": false, "profile_use_background_image": true, "location": "", "notifications": false, "favourites_count": 2709, "profile_background_image_url_https": "https://abs.twimg.com/images/themes/theme5/bg.gif", "profile_text_color": "3E4415", "profile_background_color": "352726", "contributors_enabled": false, "translator_type": "none"}, "id_str": "613500608230895619", "truncated": false, "id": 613500608230895619, "favorite_count": 1, "entities": {"user_mentions": [], "urls": [], "hashtags": [{"indices": [32, 39], "text": "ironia"}], "symbols": []}, "retweet_count": 0, "in_reply_to_user_id": null, "place": null, "geo": null, "coordinates": null, "in_reply_to_screen_name": null, "retweeted": false, "is_quote_status": false, "text": "Me encanta la noche de San Juan #ironia", "in_reply_to_status_id": null, "source": "<a href=\"http://twitter.com/download/android\" rel=\"nofollow\">Twitter for Android</a>", "contributors": null, "in_reply_to_status_id_str": null, "created_at": "Wed Jun 24 00:15:17 +0000 2015", "favorited": false, "in_reply_to_user_id_str": null}