{"extended_entities": {"media": [{"media_url": "http://pbs.twimg.com/media/CIg_AIJXAAA4cna.jpg", "expanded_url": "https://twitter.com/CotiConsolini/status/614810669100204032/photo/1", "id_str": "614810620555362304", "media_url_https": "https://pbs.twimg.com/media/CIg_AIJXAAA4cna.jpg", "sizes": {"small": {"w": 383, "h": 680, "resize": "fit"}, "large": {"w": 576, "h": 1024, "resize": "fit"}, "thumb": {"w": 150, "h": 150, "resize": "crop"}, "medium": {"w": 576, "h": 1024, "resize": "fit"}}, "type": "photo", "url": "http://t.co/okgNul6fMT", "display_url": "pic.twitter.com/okgNul6fMT", "indices": [83, 105], "id": 614810620555362304}]}, "created_at": "Sat Jun 27 15:01:00 +0000 2015", "lang": "es", "is_quote_status": false, "text": "Viva la diversidad. @KevingstonOK da el ejemplo. #ironia #jodetexgrandote #pagamas http://t.co/okgNul6fMT", "in_reply_to_status_id": null, "entities": {"symbols": [], "hashtags": [{"indices": [49, 56], "text": "ironia"}, {"indices": [57, 73], "text": "jodetexgrandote"}, {"indices": [74, 82], "text": "pagamas"}], "user_mentions": [{"id_str": "184546010", "screen_name": "KevingstonOK", "name": "KEVINGSTON", "indices": [20, 33], "id": 184546010}], "urls": [], "media": [{"media_url": "http://pbs.twimg.com/media/CIg_AIJXAAA4cna.jpg", "expanded_url": "https://twitter.com/CotiConsolini/status/614810669100204032/photo/1", "id_str": "614810620555362304", "media_url_https": "https://pbs.twimg.com/media/CIg_AIJXAAA4cna.jpg", "sizes": {"small": {"w": 383, "h": 680, "resize": "fit"}, "large": {"w": 576, "h": 1024, "resize": "fit"}, "thumb": {"w": 150, "h": 150, "resize": "crop"}, "medium": {"w": 576, "h": 1024, "resize": "fit"}}, "type": "photo", "url": "http://t.co/okgNul6fMT", "display_url": "pic.twitter.com/okgNul6fMT", "indices": [83, 105], "id": 614810620555362304}]}, "truncated": false, "favorited": false, "user": {"favourites_count": 23, "created_at": "Thu Jun 16 15:26:12 +0000 2011", "lang": "es", "protected": false, "listed_count": 1, "profile_image_url_https": "https://pbs.twimg.com/profile_images/768814498018885632/k1tArHia_normal.jpg", "profile_background_image_url": "http://abs.twimg.com/images/themes/theme18/bg.gif", "entities": {"description": {"urls": []}}, "follow_request_sent": false, "default_profile_image": false, "notifications": false, "friends_count": 116, "location": "", "id_str": "318486122", "utc_offset": null, "profile_image_url": "http://pbs.twimg.com/profile_images/768814498018885632/k1tArHia_normal.jpg", "has_extended_profile": false, "screen_name": "CotiConsolini", "id": 318486122, "followers_count": 46, "time_zone": null, "profile_sidebar_border_color": "FFFFFF", "description": "", "statuses_count": 123, "name": "Coti", "profile_background_color": "FAFFFE", "geo_enabled": false, "profile_banner_url": "https://pbs.twimg.com/profile_banners/318486122/1405616552", "contributors_enabled": false, "profile_sidebar_fill_color": "F6F6F6", "default_profile": false, "verified": false, "profile_background_image_url_https": "https://abs.twimg.com/images/themes/theme18/bg.gif", "profile_use_background_image": false, "is_translation_enabled": false, "is_translator": false, "following": false, "profile_link_color": "FF6B6B", "translator_type": "none", "url": null, "profile_background_tile": false, "profile_text_color": "333333"}, "retweeted": false, "in_reply_to_user_id": null, "id": 614810669100204032, "retweet_count": 0, "geo": null, "possibly_sensitive": false, "contributors": null, "in_reply_to_status_id_str": null, "id_str": "614810669100204032", "in_reply_to_screen_name": null, "coordinates": null, "source": "<a href=\"http://twitter.com/download/android\" rel=\"nofollow\">Twitter for Android</a>", "in_reply_to_user_id_str": null, "favorite_count": 0, "place": null}