{"source": "<a href=\"http://twitter.com/download/android\" rel=\"nofollow\">Twitter for Android</a>", "created_at": "Mon Jun 29 00:31:22 +0000 2015", "lang": "es", "is_quote_status": false, "text": "Pues me encanta esto de no poder dormir #ironia", "in_reply_to_status_id": null, "entities": {"symbols": [], "hashtags": [{"indices": [40, 47], "text": "ironia"}], "user_mentions": [], "urls": []}, "truncated": false, "favorited": false, "user": {"favourites_count": 16300, "created_at": "Wed Dec 14 15:30:00 +0000 2011", "lang": "es", "protected": false, "listed_count": 6, "profile_image_url_https": "https://pbs.twimg.com/profile_images/985847929847021568/ZnP1o5LG_normal.jpg", "profile_background_image_url": "http://abs.twimg.com/images/themes/theme1/bg.png", "entities": {"description": {"urls": []}}, "follow_request_sent": false, "default_profile_image": false, "notifications": false, "friends_count": 441, "location": "Madrid, Comunidad de Madrid", "id_str": "436780242", "utc_offset": null, "profile_image_url": "http://pbs.twimg.com/profile_images/985847929847021568/ZnP1o5LG_normal.jpg", "has_extended_profile": true, "screen_name": "laia_lafuente", "id": 436780242, "followers_count": 659, "time_zone": null, "profile_sidebar_border_color": "FFFFFF", "description": "21. Tal vez te duela, pero desde que te fuiste, me siento mucho mejor. #BeYourself\n\u00a0\u2640                                                   Barcelona - Madrid", "statuses_count": 21068, "name": "Laia Lafuente", "profile_background_color": "B700FF", "geo_enabled": true, "profile_banner_url": "https://pbs.twimg.com/profile_banners/436780242/1463823179", "contributors_enabled": false, "profile_sidebar_fill_color": "FF007B", "default_profile": false, "verified": false, "profile_background_image_url_https": "https://abs.twimg.com/images/themes/theme1/bg.png", "profile_use_background_image": true, "is_translation_enabled": false, "is_translator": false, "following": false, "profile_link_color": "FA0071", "translator_type": "none", "url": null, "profile_background_tile": true, "profile_text_color": "BC00FA"}, "retweeted": false, "in_reply_to_user_id": null, "id": 615316593900437504, "retweet_count": 0, "geo": null, "contributors": null, "in_reply_to_status_id_str": null, "id_str": "615316593900437504", "in_reply_to_screen_name": null, "coordinates": null, "in_reply_to_user_id_str": null, "favorite_count": 0, "place": null}