{"source": "<a href=\"http://twitter.com/download/android\" rel=\"nofollow\">Twitter for Android</a>", "created_at": "Mon Jun 29 02:52:50 +0000 2015", "lang": "es", "is_quote_status": false, "text": "Extendieron las primarias del Psuv hasta las 10 pm por este gent\u00edo en las colas #SARCASMO http://t.co/J7XjwrRNu2 v\u00eda @la_patilla", "in_reply_to_status_id": null, "entities": {"symbols": [], "hashtags": [{"indices": [80, 89], "text": "SARCASMO"}], "user_mentions": [{"id_str": "124172948", "screen_name": "la_patilla", "name": "La Patilla", "indices": [117, 128], "id": 124172948}], "urls": [{"expanded_url": "http://www.lapatilla.com/site/2015/06/28/extendieron-las-primarias-del-psuv-hasta-las-10-pm-por-este-gentio-en-las-colas-sarcasmo/", "indices": [90, 112], "url": "http://t.co/J7XjwrRNu2", "display_url": "lapatilla.com/site/2015/06/2\u2026"}]}, "truncated": false, "favorited": false, "user": {"favourites_count": 1513, "created_at": "Sun Mar 27 01:57:51 +0000 2011", "lang": "es", "protected": false, "listed_count": 55, "profile_image_url_https": "https://pbs.twimg.com/profile_images/447894859685572608/XNPURm_j_normal.jpeg", "profile_background_image_url": "http://abs.twimg.com/images/themes/theme9/bg.gif", "entities": {"description": {"urls": []}, "url": {"urls": [{"expanded_url": "http://www.chuchoenlosdeportes.blogspot.com", "indices": [0, 23], "url": "https://t.co/Hb9GzKhplM", "display_url": "chuchoenlosdeportes.blogspot.com"}]}}, "follow_request_sent": false, "default_profile_image": false, "notifications": false, "friends_count": 2438, "location": "Maracay, Venezuela", "id_str": "272718962", "utc_offset": null, "profile_image_url": "http://pbs.twimg.com/profile_images/447894859685572608/XNPURm_j_normal.jpeg", "has_extended_profile": true, "screen_name": "roldanjesus", "id": 272718962, "followers_count": 2109, "time_zone": null, "profile_sidebar_border_color": "181A1E", "description": "Periodista que le gusta el DEPORTE, y la COCINA...DEM\u00d3CRATA Instagram: jesusroldan chucho", "statuses_count": 95104, "name": "Jes\u00fas Chucho", "profile_background_color": "1A1B1F", "geo_enabled": true, "profile_banner_url": "https://pbs.twimg.com/profile_banners/272718962/1517610292", "contributors_enabled": false, "profile_sidebar_fill_color": "252429", "default_profile": false, "verified": false, "profile_background_image_url_https": "https://abs.twimg.com/images/themes/theme9/bg.gif", "profile_use_background_image": true, "is_translation_enabled": true, "is_translator": false, "following": false, "profile_link_color": "1111EB", "translator_type": "none", "url": "https://t.co/Hb9GzKhplM", "profile_background_tile": false, "profile_text_color": "F2F3F7"}, "retweeted": false, "in_reply_to_user_id": null, "id": 615352195186335744, "retweet_count": 0, "geo": null, "possibly_sensitive": false, "contributors": null, "in_reply_to_status_id_str": null, "id_str": "615352195186335744", "in_reply_to_screen_name": null, "coordinates": null, "in_reply_to_user_id_str": null, "favorite_count": 0, "place": null}