{"lang": "es", "possibly_sensitive": false, "user": {"profile_sidebar_fill_color": "F6F6F6", "following": false, "profile_banner_url": "https://pbs.twimg.com/profile_banners/293564071/1398410572", "screen_name": "angie_dong", "geo_enabled": true, "lang": "es", "friends_count": 491, "id_str": "293564071", "profile_link_color": "4A913C", "has_extended_profile": true, "id": 293564071, "profile_background_tile": true, "entities": {"description": {"urls": []}, "url": {"urls": [{"indices": [0, 22], "display_url": "instagram.com/angie_dong", "url": "http://t.co/ysVzXWLkBN", "expanded_url": "http://www.instagram.com/angie_dong"}]}}, "description": "La gente es m\u00e1s moral de lo que cree, y m\u00e1s amoral de lo que se puede imaginar.", "is_translation_enabled": false, "time_zone": null, "default_profile": false, "profile_image_url_https": "https://pbs.twimg.com/profile_images/378800000408460590/27f9b8f257be11d623ee5846d8124e52_normal.jpeg", "follow_request_sent": false, "default_profile_image": false, "profile_background_image_url": "http://abs.twimg.com/images/themes/theme18/bg.gif", "listed_count": 5, "profile_sidebar_border_color": "FFFFFF", "name": "ANGIE ALEJANDRA D.G.", "followers_count": 180, "url": "http://t.co/ysVzXWLkBN", "is_translator": false, "utc_offset": null, "protected": false, "statuses_count": 2666, "created_at": "Thu May 05 15:30:12 +0000 2011", "profile_image_url": "http://pbs.twimg.com/profile_images/378800000408460590/27f9b8f257be11d623ee5846d8124e52_normal.jpeg", "verified": false, "profile_use_background_image": true, "location": "COLOMBIA", "notifications": false, "favourites_count": 357, "profile_background_image_url_https": "https://abs.twimg.com/images/themes/theme18/bg.gif", "profile_text_color": "333333", "profile_background_color": "131516", "contributors_enabled": false, "translator_type": "none"}, "id_str": "616808916308070401", "truncated": false, "id": 616808916308070401, "in_reply_to_screen_name": "SofiaVergara", "entities": {"user_mentions": [{"indices": [0, 13], "id_str": "91390383", "screen_name": "SofiaVergara", "name": "Sofia Vergara", "id": 91390383}], "urls": [{"indices": [117, 140], "display_url": "twitter.com/WBPicturesLata\u2026", "url": "https://t.co/jGbKxknj6b", "expanded_url": "https://twitter.com/WBPicturesLatam/status/616349845402443778"}], "hashtags": [{"indices": [73, 82], "text": "sarcasmo"}], "symbols": []}, "quoted_status_id": 616349845402443778, "retweet_count": 0, "in_reply_to_user_id": 91390383, "place": null, "quoted_status": {"lang": "es", "possibly_sensitive": false, "user": {"profile_sidebar_fill_color": "000000", "following": false, "profile_banner_url": "https://pbs.twimg.com/profile_banners/436258074/1538756206", "screen_name": "WBPicturesLatam", "geo_enabled": true, "lang": "es", "friends_count": 341, "id_str": "436258074", "profile_link_color": "3B94D9", "has_extended_profile": false, "id": 436258074, "profile_background_tile": false, "entities": {"description": {"urls": []}, "url": {"urls": [{"indices": [0, 23], "display_url": "warnerbroslatino.com", "url": "https://t.co/pRahOsRfEY", "expanded_url": "http://www.warnerbroslatino.com/"}]}}, "description": "Cuenta oficial de Warner Bros. Pictures Latinoam\u00e9rica.", "is_translation_enabled": false, "time_zone": null, "default_profile": false, "profile_image_url_https": "https://pbs.twimg.com/profile_images/716081069267750913/2u-c7L29_normal.jpg", "follow_request_sent": false, "default_profile_image": false, "profile_background_image_url": "http://abs.twimg.com/images/themes/theme1/bg.png", "listed_count": 93, "profile_sidebar_border_color": "000000", "name": "WB Pictures Latam", "followers_count": 25498, "url": "https://t.co/pRahOsRfEY", "is_translator": false, "utc_offset": null, "protected": false, "statuses_count": 4612, "created_at": "Wed Dec 14 00:03:48 +0000 2011", "profile_image_url": "http://pbs.twimg.com/profile_images/716081069267750913/2u-c7L29_normal.jpg", "verified": true, "profile_use_background_image": false, "location": "Latinoam\u00e9rica", "notifications": false, "favourites_count": 3588, "profile_background_image_url_https": "https://abs.twimg.com/images/themes/theme1/bg.png", "profile_text_color": "000000", "profile_background_color": "000000", "contributors_enabled": false, "translator_type": "none"}, "id_str": "616349845402443778", "truncated": false, "id": 616349845402443778, "favorite_count": 225, "entities": {"user_mentions": [{"indices": [42, 55], "id_str": "91390383", "screen_name": "SofiaVergara", "name": "Sofia Vergara", "id": 91390383}, {"indices": [58, 71], "id_str": "1198406491", "screen_name": "RWitherspoon", "name": "Reese Witherspoon", "id": 1198406491}], "urls": [{"indices": [111, 134], "display_url": "amp.twimg.com/v/cbf1aa58-336\u2026", "url": "https://t.co/jE9y1pdo2t", "expanded_url": "https://amp.twimg.com/v/cbf1aa58-3360-4525-866c-1484e2565701"}], "hashtags": [{"indices": [94, 109], "text": "DosLocasEnFuga"}], "symbols": []}, "retweet_count": 158, "scopes": {"followers": false}, "in_reply_to_user_id": null, "place": null, "geo": null, "coordinates": null, "in_reply_to_screen_name": null, "retweeted": false, "is_quote_status": false, "text": "\u00a1Atenci\u00f3n, Colombia! El 9 de julio llegan @SofiaVergara y @RWitherspoon a todos los cines con #DosLocasEnFuga \nhttps://t.co/jE9y1pdo2t", "in_reply_to_status_id": null, "source": "<a href=\"http://twitter.com\" rel=\"nofollow\">Twitter Web Client</a>", "contributors": null, "in_reply_to_status_id_str": null, "created_at": "Wed Jul 01 20:57:09 +0000 2015", "favorited": false, "in_reply_to_user_id_str": null}, "geo": null, "favorite_count": 0, "coordinates": null, "quoted_status_id_str": "616349845402443778", "retweeted": false, "is_quote_status": true, "text": "@SofiaVergara se la juega a su compa\u00f1era de la manera m\u00e1s latina posible #sarcasmo y como dicen\"confunde y reinaras\" https://t.co/jGbKxknj6b", "in_reply_to_status_id": null, "source": "<a href=\"http://twitter.com\" rel=\"nofollow\">Twitter Web Client</a>", "contributors": null, "in_reply_to_status_id_str": null, "created_at": "Fri Jul 03 03:21:20 +0000 2015", "favorited": false, "in_reply_to_user_id_str": "91390383"}