{"source": "<a href=\"http://twitter.com/download/android\" rel=\"nofollow\">Twitter for Android</a>", "created_at": "Wed Jul 15 00:24:40 +0000 2015", "lang": "es", "is_quote_status": false, "text": "Por fin, ma\u00f1ana ser\u00e1 un d\u00eda muy bonito, llego mi cumplea\u00f1os n\u00famero 15, pareciera que fue ayer cuando nac\u00ed. \n\n#Sarcasmo #Jajaja #22 #Shalom", "in_reply_to_status_id": null, "entities": {"symbols": [], "hashtags": [{"indices": [109, 118], "text": "Sarcasmo"}, {"indices": [119, 126], "text": "Jajaja"}, {"indices": [131, 138], "text": "Shalom"}], "user_mentions": [], "urls": []}, "truncated": false, "favorited": false, "user": {"favourites_count": 2452, "created_at": "Sat Nov 20 14:14:46 +0000 2010", "lang": "es", "protected": false, "listed_count": 4, "profile_image_url_https": "https://pbs.twimg.com/profile_images/448922344623308800/-NMSMHmD_normal.jpeg", "profile_background_image_url": "http://abs.twimg.com/images/themes/theme1/bg.png", "entities": {"description": {"urls": [{"expanded_url": "http://keanshalom.wordpress.com", "indices": [67, 90], "url": "https://t.co/FM5w287Fvz", "display_url": "keanshalom.wordpress.com"}]}, "url": {"urls": [{"expanded_url": "http://about.me/talmidangel", "indices": [0, 23], "url": "https://t.co/qrgR1O2geG", "display_url": "about.me/talmidangel"}]}}, "follow_request_sent": false, "default_profile_image": false, "notifications": false, "friends_count": 1380, "location": "Chiapas, M\u00e9xico", "id_str": "217778148", "utc_offset": null, "profile_image_url": "http://pbs.twimg.com/profile_images/448922344623308800/-NMSMHmD_normal.jpeg", "has_extended_profile": true, "screen_name": "TalmidMalak", "id": 217778148, "followers_count": 532, "time_zone": null, "profile_sidebar_border_color": "FFFFFF", "description": "TALMID| Amigo | Consejero| Escritor | apasionado por la juventud.. https://t.co/FM5w287Fvz", "statuses_count": 6011, "name": "Talmid \u00c1ngel Ruiz", "profile_background_color": "C0DEED", "geo_enabled": true, "profile_banner_url": "https://pbs.twimg.com/profile_banners/217778148/1455030066", "contributors_enabled": false, "profile_sidebar_fill_color": "DDEEF6", "default_profile": false, "verified": false, "profile_background_image_url_https": "https://abs.twimg.com/images/themes/theme1/bg.png", "profile_use_background_image": true, "is_translation_enabled": false, "is_translator": false, "following": false, "profile_link_color": "1B95E0", "translator_type": "none", "url": "https://t.co/qrgR1O2geG", "profile_background_tile": true, "profile_text_color": "333333"}, "retweeted": false, "in_reply_to_user_id": null, "id": 621113113107042304, "retweet_count": 0, "geo": null, "contributors": null, "in_reply_to_status_id_str": null, "id_str": "621113113107042304", "in_reply_to_screen_name": null, "coordinates": null, "in_reply_to_user_id_str": null, "favorite_count": 0, "place": null}