{"source": "<a href=\"http://twitter.com\" rel=\"nofollow\">Twitter Web Client</a>", "created_at": "Wed Jul 22 13:43:36 +0000 2015", "lang": "es", "is_quote_status": false, "text": "Me encanta el apoyo que tengo siempre de mis padres #Iron\u00eda", "in_reply_to_status_id": null, "entities": {"symbols": [], "hashtags": [{"indices": [52, 59], "text": "Iron\u00eda"}], "user_mentions": [], "urls": []}, "truncated": false, "favorited": false, "user": {"favourites_count": 10661, "created_at": "Sun Sep 25 12:24:26 +0000 2011", "lang": "es", "protected": false, "listed_count": 15, "profile_image_url_https": "https://pbs.twimg.com/profile_images/1027935606989639681/DDvQSb3L_normal.jpg", "profile_background_image_url": "http://abs.twimg.com/images/themes/theme1/bg.png", "entities": {"description": {"urls": []}}, "follow_request_sent": false, "default_profile_image": false, "notifications": false, "friends_count": 751, "location": "Doble Grado de Historia+Historia del Arte (UCO)", "id_str": "379705718", "utc_offset": null, "profile_image_url": "http://pbs.twimg.com/profile_images/1027935606989639681/DDvQSb3L_normal.jpg", "has_extended_profile": true, "screen_name": "Pacoli_", "id": 379705718, "followers_count": 1628, "time_zone": null, "profile_sidebar_border_color": "C0DEED", "description": "Con la m\u00fasica hemos topado. T\u00f3 es pa n\u00e1. @BMLAESPERANZA. \u00a1Cai!", "statuses_count": 9267, "name": "Pacoli", "profile_background_color": "C0DEED", "geo_enabled": true, "profile_banner_url": "https://pbs.twimg.com/profile_banners/379705718/1470227197", "contributors_enabled": false, "profile_sidebar_fill_color": "DDEEF6", "default_profile": false, "verified": false, "profile_background_image_url_https": "https://abs.twimg.com/images/themes/theme1/bg.png", "profile_use_background_image": true, "is_translation_enabled": false, "is_translator": false, "following": false, "profile_link_color": "981CEB", "translator_type": "regular", "url": null, "profile_background_tile": false, "profile_text_color": "333333"}, "retweeted": false, "in_reply_to_user_id": null, "id": 623850887027499008, "retweet_count": 0, "geo": null, "contributors": null, "in_reply_to_status_id_str": null, "id_str": "623850887027499008", "in_reply_to_screen_name": null, "coordinates": null, "in_reply_to_user_id_str": null, "favorite_count": 2, "place": null}