{"in_reply_to_user_id": null, "in_reply_to_screen_name": null, "truncated": false, "place": null, "favorited": false, "user": {"time_zone": null, "url": null, "utc_offset": null, "profile_background_image_url_https": "https://abs.twimg.com/images/themes/theme1/bg.png", "is_translator": false, "verified": false, "followers_count": 107, "profile_background_tile": true, "screen_name": "malistephanie", "profile_banner_url": "https://pbs.twimg.com/profile_banners/74041588/1536558096", "name": "StepheNie", "geo_enabled": true, "profile_link_color": "700445", "listed_count": 0, "profile_use_background_image": true, "profile_sidebar_border_color": "000000", "default_profile_image": false, "is_translation_enabled": false, "id_str": "74041588", "created_at": "Mon Sep 14 02:17:24 +0000 2009", "has_extended_profile": true, "contributors_enabled": false, "favourites_count": 756, "profile_sidebar_fill_color": "332639", "following": false, "lang": "en", "entities": {"description": {"urls": []}}, "friends_count": 185, "profile_background_color": "AA791A", "description": "sometimes I'm Lazy,I'm Picky & I Feel HapPy, I Make WisheS...I Have DreaMs:::::a little luck can go a long way so I don't Worry 'bOut PeoplE Say ;)", "default_profile": false, "profile_image_url_https": "https://pbs.twimg.com/profile_images/956725056578703360/8DzcfyoX_normal.jpg", "id": 74041588, "protected": false, "notifications": false, "statuses_count": 3176, "location": "mexicO", "follow_request_sent": false, "profile_image_url": "http://pbs.twimg.com/profile_images/956725056578703360/8DzcfyoX_normal.jpg", "profile_text_color": "71703E", "translator_type": "none", "profile_background_image_url": "http://abs.twimg.com/images/themes/theme1/bg.png"}, "id_str": "609027109575524352", "created_at": "Thu Jun 11 15:59:12 +0000 2015", "in_reply_to_status_id_str": null, "in_reply_to_user_id_str": null, "lang": "es", "retweeted": false, "entities": {"hashtags": [{"indices": [99, 109], "text": "justsayin"}, {"indices": [110, 117], "text": "Ironia"}], "urls": [], "user_mentions": [], "symbols": []}, "coordinates": null, "favorite_count": 1, "id": 609027109575524352, "is_quote_status": false, "retweet_count": 0, "geo": null, "text": "Cuando tienes 5 a\u00f1os y te invitan a su casa \"a ver tele\" esta bien, pero no cuando tienen 30 a\u00f1os. #justsayin #Ironia", "contributors": null, "source": "<a href=\"http://twitter.com/download/iphone\" rel=\"nofollow\">Twitter for iPhone</a>", "in_reply_to_status_id": null}