{"text": "No entend\u00ed lo de poco despeinado #sarcasmo.. :** https://t.co/CHPso7Pki3", "in_reply_to_status_id_str": null, "source": "<a href=\"http://twitter.com/download/android\" rel=\"nofollow\">Twitter for Android</a>", "created_at": "Thu Jun 11 20:40:36 +0000 2015", "quoted_status": {"text": "Un poco despeinado pero feliz de estar contigo @clemen72 tqmmmmm http://t.co/kmcoue7ybW", "in_reply_to_status_id_str": null, "source": "<a href=\"http://twitter.com/download/iphone\" rel=\"nofollow\">Twitter for iPhone</a>", "created_at": "Thu Jun 11 20:36:17 +0000 2015", "in_reply_to_user_id": null, "lang": "es", "user": {"profile_text_color": "666666", "created_at": "Mon Jun 28 06:56:35 +0000 2010", "following": false, "profile_background_tile": false, "profile_sidebar_border_color": "181A1E", "is_translator": false, "profile_background_image_url_https": "https://abs.twimg.com/images/themes/theme9/bg.gif", "notifications": false, "location": "Hermosillo Sonora", "lang": "es", "verified": false, "name": "Edgar Melendrez R. \ud83c\udf35", "profile_background_color": "1A1B1F", "description": "Orgullosamente de #SONORA \ud83c\udf35 #PADRESISTA La sangre te hace pariente.. Pero la Lealtad te hace familia!!!!!", "geo_enabled": true, "is_translation_enabled": false, "protected": false, "listed_count": 8, "translator_type": "none", "contributors_enabled": false, "has_extended_profile": true, "follow_request_sent": false, "utc_offset": null, "profile_background_image_url": "http://abs.twimg.com/images/themes/theme9/bg.gif", "profile_sidebar_fill_color": "252429", "screen_name": "EdgarmRe", "id": 160462194, "statuses_count": 17390, "friends_count": 1929, "default_profile_image": false, "id_str": "160462194", "profile_banner_url": "https://pbs.twimg.com/profile_banners/160462194/1538456837", "favourites_count": 12369, "profile_link_color": "E01212", "profile_image_url": "http://pbs.twimg.com/profile_images/970220464395100160/lZRwvx5Q_normal.jpg", "followers_count": 1311, "time_zone": null, "profile_use_background_image": true, "entities": {"description": {"urls": []}}, "profile_image_url_https": "https://pbs.twimg.com/profile_images/970220464395100160/lZRwvx5Q_normal.jpg", "url": null, "default_profile": false}, "place": null, "in_reply_to_status_id": null, "is_quote_status": false, "retweeted": false, "contributors": null, "possibly_sensitive": false, "in_reply_to_screen_name": null, "coordinates": null, "in_reply_to_user_id_str": null, "id": 609096840655454208, "truncated": false, "favorited": false, "retweet_count": 6, "entities": {"urls": [], "hashtags": [], "media": [{"id": 609096824490569729, "sizes": {"thumb": {"w": 150, "resize": "crop", "h": 150}, "small": {"w": 510, "resize": "fit", "h": 680}, "large": {"w": 768, "resize": "fit", "h": 1024}, "medium": {"w": 768, "resize": "fit", "h": 1024}}, "media_url": "http://pbs.twimg.com/media/CHPyVbGUMAEUj-Z.jpg", "type": "photo", "expanded_url": "https://twitter.com/EdgarmRe/status/609096840655454208/photo/1", "media_url_https": "https://pbs.twimg.com/media/CHPyVbGUMAEUj-Z.jpg", "indices": [65, 87], "display_url": "pic.twitter.com/kmcoue7ybW", "id_str": "609096824490569729", "url": "http://t.co/kmcoue7ybW"}], "symbols": [], "user_mentions": [{"name": "Clemen El\u00edas", "id": 273208071, "indices": [47, 56], "id_str": "273208071", "screen_name": "clemen72"}]}, "extended_entities": {"media": [{"id": 609096824490569729, "sizes": {"thumb": {"w": 150, "resize": "crop", "h": 150}, "small": {"w": 510, "resize": "fit", "h": 680}, "large": {"w": 768, "resize": "fit", "h": 1024}, "medium": {"w": 768, "resize": "fit", "h": 1024}}, "media_url": "http://pbs.twimg.com/media/CHPyVbGUMAEUj-Z.jpg", "type": "photo", "expanded_url": "https://twitter.com/EdgarmRe/status/609096840655454208/photo/1", "media_url_https": "https://pbs.twimg.com/media/CHPyVbGUMAEUj-Z.jpg", "indices": [65, 87], "display_url": "pic.twitter.com/kmcoue7ybW", "id_str": "609096824490569729", "url": "http://t.co/kmcoue7ybW"}, {"id": 609096824578674688, "sizes": {"thumb": {"w": 150, "resize": "crop", "h": 150}, "small": {"w": 510, "resize": "fit", "h": 680}, "large": {"w": 768, "resize": "fit", "h": 1024}, "medium": {"w": 768, "resize": "fit", "h": 1024}}, "media_url": "http://pbs.twimg.com/media/CHPyVbbUkAAaTb8.jpg", "type": "photo", "expanded_url": "https://twitter.com/EdgarmRe/status/609096840655454208/photo/1", "media_url_https": "https://pbs.twimg.com/media/CHPyVbbUkAAaTb8.jpg", "indices": [65, 87], "display_url": "pic.twitter.com/kmcoue7ybW", "id_str": "609096824578674688", "url": "http://t.co/kmcoue7ybW"}]}, "favorite_count": 5, "id_str": "609096840655454208", "geo": null}, "in_reply_to_user_id": null, "lang": "es", "user": {"profile_text_color": "D6ED2B", "created_at": "Fri Jul 09 22:51:38 +0000 2010", "following": false, "profile_background_tile": true, "profile_sidebar_border_color": "FFFFFF", "is_translator": false, "profile_background_image_url_https": "https://abs.twimg.com/images/themes/theme5/bg.gif", "notifications": false, "location": "", "lang": "es", "verified": false, "name": "Jael Esparza", "profile_background_color": "4D3A05", "description": "#packersfan                                   \n                                 Lo que escribo en este espacio es a t\u00edtulo personal", "geo_enabled": false, "is_translation_enabled": false, "protected": false, "listed_count": 25, "translator_type": "none", "contributors_enabled": false, "has_extended_profile": true, "follow_request_sent": false, "utc_offset": null, "profile_background_image_url": "http://abs.twimg.com/images/themes/theme5/bg.gif", "profile_sidebar_fill_color": "000000", "screen_name": "JaelEsparza", "id": 164849481, "statuses_count": 38576, "friends_count": 932, "default_profile_image": false, "id_str": "164849481", "profile_banner_url": "https://pbs.twimg.com/profile_banners/164849481/1471575552", "favourites_count": 1120, "profile_link_color": "D13E08", "profile_image_url": "http://pbs.twimg.com/profile_images/875200870702604289/8lw-AsCr_normal.jpg", "followers_count": 2781, "time_zone": null, "profile_use_background_image": true, "entities": {"description": {"urls": []}}, "profile_image_url_https": "https://pbs.twimg.com/profile_images/875200870702604289/8lw-AsCr_normal.jpg", "url": null, "default_profile": false}, "place": null, "in_reply_to_status_id": null, "is_quote_status": true, "quoted_status_id": 609096840655454208, "retweeted": false, "contributors": null, "possibly_sensitive": false, "in_reply_to_screen_name": null, "coordinates": null, "quoted_status_id_str": "609096840655454208", "in_reply_to_user_id_str": null, "id": 609097926489419776, "truncated": false, "favorited": false, "retweet_count": 1, "entities": {"urls": [{"expanded_url": "https://twitter.com/EdgarmRe/status/609096840655454208", "indices": [49, 72], "display_url": "twitter.com/EdgarmRe/statu\u2026", "url": "https://t.co/CHPso7Pki3"}], "hashtags": [{"text": "sarcasmo", "indices": [33, 42]}], "symbols": [], "user_mentions": []}, "favorite_count": 1, "id_str": "609097926489419776", "geo": null}