{"text": "Cuando tienes 5 a\u00f1os y te invitan a su casa \"a ver tele\" esta bien, pero no cuando tienen 30 a\u00f1os. #justsayin #Ironia", "in_reply_to_status_id_str": null, "source": "<a href=\"http://twitter.com/download/iphone\" rel=\"nofollow\">Twitter for iPhone</a>", "created_at": "Thu Jun 11 15:59:12 +0000 2015", "in_reply_to_user_id": null, "lang": "es", "user": {"profile_text_color": "71703E", "created_at": "Mon Sep 14 02:17:24 +0000 2009", "following": false, "profile_background_tile": true, "profile_sidebar_border_color": "000000", "is_translator": false, "profile_background_image_url_https": "https://abs.twimg.com/images/themes/theme1/bg.png", "notifications": false, "location": "mexicO", "lang": "en", "verified": false, "name": "StepheNie", "profile_background_color": "AA791A", "description": "sometimes I'm Lazy,I'm Picky & I Feel HapPy, I Make WisheS...I Have DreaMs:::::a little luck can go a long way so I don't Worry 'bOut PeoplE Say ;)", "geo_enabled": true, "is_translation_enabled": false, "protected": false, "listed_count": 0, "translator_type": "none", "contributors_enabled": false, "has_extended_profile": true, "follow_request_sent": false, "utc_offset": null, "profile_background_image_url": "http://abs.twimg.com/images/themes/theme1/bg.png", "profile_sidebar_fill_color": "332639", "screen_name": "malistephanie", "id": 74041588, "statuses_count": 3176, "friends_count": 185, "default_profile_image": false, "id_str": "74041588", "profile_banner_url": "https://pbs.twimg.com/profile_banners/74041588/1536558096", "favourites_count": 756, "profile_link_color": "700445", "profile_image_url": "http://pbs.twimg.com/profile_images/956725056578703360/8DzcfyoX_normal.jpg", "followers_count": 107, "time_zone": null, "profile_use_background_image": true, "entities": {"description": {"urls": []}}, "profile_image_url_https": "https://pbs.twimg.com/profile_images/956725056578703360/8DzcfyoX_normal.jpg", "url": null, "default_profile": false}, "place": null, "in_reply_to_status_id": null, "is_quote_status": false, "retweeted": false, "contributors": null, "in_reply_to_screen_name": null, "coordinates": null, "in_reply_to_user_id_str": null, "id": 609027109575524352, "truncated": false, "favorited": false, "retweet_count": 0, "entities": {"urls": [], "hashtags": [{"text": "justsayin", "indices": [99, 109]}, {"text": "Ironia", "indices": [110, 117]}], "symbols": [], "user_mentions": []}, "favorite_count": 1, "id_str": "609027109575524352", "geo": null}