{"text": "Siempre lo mimo. El que me gusta no le gusto y al que no me gusta le gusto. #damn #cosasdelavida #ironia", "in_reply_to_status_id_str": null, "source": "<a href=\"http://twitter.com/download/iphone\" rel=\"nofollow\">Twitter for iPhone</a>", "created_at": "Sun Jun 14 19:37:25 +0000 2015", "in_reply_to_user_id": null, "lang": "es", "user": {"profile_text_color": "333333", "created_at": "Thu Jan 28 18:44:58 +0000 2010", "following": false, "profile_background_tile": true, "profile_sidebar_border_color": "C0DEED", "is_translator": false, "profile_background_image_url_https": "https://abs.twimg.com/images/themes/theme1/bg.png", "notifications": false, "location": "Cix", "lang": "es", "verified": false, "name": "BnJ", "profile_background_color": "353738", "description": "my mother, games, music, movies, friends, animals and books. I am green. Peruvian blood flows all over my viens. I am seriously funny. I don't go straight.", "geo_enabled": false, "is_translation_enabled": false, "protected": false, "listed_count": 4, "translator_type": "none", "contributors_enabled": false, "has_extended_profile": true, "follow_request_sent": false, "utc_offset": null, "profile_background_image_url": "http://abs.twimg.com/images/themes/theme1/bg.png", "profile_sidebar_fill_color": "DDEEF6", "screen_name": "lBnjal", "id": 109338325, "statuses_count": 1246, "friends_count": 707, "default_profile_image": false, "id_str": "109338325", "profile_banner_url": "https://pbs.twimg.com/profile_banners/109338325/1477966299", "favourites_count": 613, "profile_link_color": "000000", "profile_image_url": "http://pbs.twimg.com/profile_images/793274261561569281/DJ9vsVOu_normal.jpg", "followers_count": 134, "time_zone": null, "profile_use_background_image": true, "entities": {"description": {"urls": []}}, "profile_image_url_https": "https://pbs.twimg.com/profile_images/793274261561569281/DJ9vsVOu_normal.jpg", "url": null, "default_profile": false}, "place": null, "in_reply_to_status_id": null, "is_quote_status": false, "retweeted": false, "contributors": null, "in_reply_to_screen_name": null, "coordinates": null, "in_reply_to_user_id_str": null, "id": 610169189572177920, "truncated": false, "favorited": false, "retweet_count": 0, "entities": {"urls": [], "hashtags": [{"text": "damn", "indices": [76, 81]}, {"text": "cosasdelavida", "indices": [82, 96]}, {"text": "ironia", "indices": [97, 104]}], "symbols": [], "user_mentions": []}, "favorite_count": 0, "id_str": "610169189572177920", "geo": null}