{"in_reply_to_user_id": null, "in_reply_to_screen_name": null, "truncated": false, "place": {"id": "7bc29846eabda1f2", "name": "Metepec", "contained_within": [], "url": "https://api.twitter.com/1.1/geo/id/7bc29846eabda1f2.json", "country_code": "MX", "attributes": {}, "full_name": "Metepec, M\u00e9xico", "country": "Mexico", "bounding_box": {"coordinates": [[[-99.6470277, 19.2156239], [-99.5128011, 19.2156239], [-99.5128011, 19.2874368], [-99.6470277, 19.2874368]]], "type": "Polygon"}, "place_type": "city"}, "favorited": false, "user": {"time_zone": null, "url": null, "utc_offset": null, "profile_background_image_url_https": "https://abs.twimg.com/images/themes/theme6/bg.gif", "is_translator": false, "verified": false, "followers_count": 162, "profile_background_tile": true, "screen_name": "MarloneGP", "profile_banner_url": "https://pbs.twimg.com/profile_banners/174827829/1410132617", "name": "Marlone Gacutan", "geo_enabled": true, "profile_link_color": "FF3300", "listed_count": 2, "profile_use_background_image": true, "profile_sidebar_border_color": "86A4A6", "default_profile_image": false, "is_translation_enabled": false, "id_str": "174827829", "created_at": "Wed Aug 04 22:54:23 +0000 2010", "has_extended_profile": true, "contributors_enabled": false, "favourites_count": 97, "profile_sidebar_fill_color": "A0C5C7", "following": false, "lang": "es", "entities": {"description": {"urls": []}}, "friends_count": 402, "profile_background_color": "709397", "description": "QFB, perfeccionista, intenso, leal e inteligente! :) Me fascina conocer gente y lugares nuevos...", "default_profile": false, "profile_image_url_https": "https://pbs.twimg.com/profile_images/609882749915103233/G5pHxAkW_normal.jpg", "id": 174827829, "protected": false, "notifications": false, "statuses_count": 2225, "location": "Mexico, Df", "follow_request_sent": false, "profile_image_url": "http://pbs.twimg.com/profile_images/609882749915103233/G5pHxAkW_normal.jpg", "profile_text_color": "333333", "translator_type": "none", "profile_background_image_url": "http://abs.twimg.com/images/themes/theme6/bg.gif"}, "id_str": "610231892797816832", "created_at": "Sun Jun 14 23:46:35 +0000 2015", "in_reply_to_status_id_str": null, "in_reply_to_user_id_str": null, "lang": "es", "retweeted": false, "entities": {"hashtags": [{"indices": [51, 58], "text": "ironia"}], "urls": [], "user_mentions": [], "symbols": []}, "coordinates": null, "favorite_count": 0, "id": 610231892797816832, "is_quote_status": false, "retweet_count": 0, "geo": null, "text": "\"Sonr\u00ede aunque no tengas motivos para hacerlo\" que #ironia", "contributors": null, "source": "<a href=\"http://twitter.com/download/iphone\" rel=\"nofollow\">Twitter for iPhone</a>", "in_reply_to_status_id": null}