{"in_reply_to_user_id": null, "in_reply_to_screen_name": null, "truncated": false, "place": null, "favorited": false, "user": {"time_zone": null, "url": null, "utc_offset": null, "profile_background_image_url_https": "https://abs.twimg.com/images/themes/theme14/bg.gif", "is_translator": false, "verified": false, "followers_count": 860, "profile_background_tile": true, "screen_name": "ClariVarela", "profile_banner_url": "https://pbs.twimg.com/profile_banners/174830538/1468201810", "name": "Cuerva  \u2764\ufe0f", "geo_enabled": true, "profile_link_color": "E81C4F", "listed_count": 8, "profile_use_background_image": true, "profile_sidebar_border_color": "000000", "default_profile_image": false, "is_translation_enabled": false, "id_str": "174830538", "created_at": "Wed Aug 04 23:03:08 +0000 2010", "has_extended_profile": true, "contributors_enabled": false, "favourites_count": 3482, "profile_sidebar_fill_color": "7AC3EE", "following": false, "lang": "es", "entities": {"description": {"urls": []}}, "friends_count": 1881, "profile_background_color": "131516", "description": "San Lorenzo \u2764\ud83d\udc99//Instragram:ClaariVarela// Lucha por lo que quer\u00e9s// Futura trabajadora social", "default_profile": false, "profile_image_url_https": "https://pbs.twimg.com/profile_images/883906460362694656/AxgcOPzX_normal.jpg", "id": 174830538, "protected": false, "notifications": false, "statuses_count": 50079, "location": "", "follow_request_sent": false, "profile_image_url": "http://pbs.twimg.com/profile_images/883906460362694656/AxgcOPzX_normal.jpg", "profile_text_color": "0C3E53", "translator_type": "none", "profile_background_image_url": "http://abs.twimg.com/images/themes/theme14/bg.gif"}, "id_str": "614596630470393857", "created_at": "Sat Jun 27 00:50:30 +0000 2015", "in_reply_to_status_id_str": null, "in_reply_to_user_id_str": null, "lang": "es", "retweeted": false, "entities": {"hashtags": [{"indices": [50, 59], "text": "Sarcasmo"}], "urls": [], "user_mentions": [], "symbols": []}, "coordinates": null, "favorite_count": 0, "id": 614596630470393857, "is_quote_status": false, "retweet_count": 0, "geo": null, "text": "Che Messi, no era que ... Sos el mejor del mundo? #Sarcasmo", "contributors": null, "source": "<a href=\"http://twitter.com/#!/download/ipad\" rel=\"nofollow\">Twitter for iPad</a>", "in_reply_to_status_id": null}