{"text": "El mi\u00e9rcoles, un dude me dijo que era muy intensa y por eso no ten\u00eda novio. \n\u00bfSer\u00e1 eso o simplemente no se me da la gana tener wey?#Sarcasmo", "in_reply_to_status_id_str": null, "source": "<a href=\"https://twitter.com/download/android\" rel=\"nofollow\">Twitter for Android Tablets</a>", "created_at": "Sat Jul 18 15:12:49 +0000 2015", "in_reply_to_user_id": null, "lang": "es", "user": {"profile_text_color": "000000", "created_at": "Tue Feb 03 22:45:58 +0000 2015", "following": false, "profile_background_tile": true, "profile_sidebar_border_color": "000000", "is_translator": false, "profile_background_image_url_https": "https://abs.twimg.com/images/themes/theme1/bg.png", "notifications": false, "location": "Quer\u00e9taro", "lang": "es", "verified": false, "name": "Adelita Le Pew \ud83c\udf38\ud83d\udc51\ud83d\udc31\ud83d\udc9a", "profile_background_color": "000000", "description": "Writer in the dark que hace rese\u00f1as de series y ensayo para su blog. Amante del cine y la literatura. Rockerilla. Crazy Cat Lady.", "geo_enabled": true, "is_translation_enabled": false, "protected": false, "listed_count": 9, "translator_type": "none", "contributors_enabled": false, "has_extended_profile": true, "follow_request_sent": false, "utc_offset": null, "profile_background_image_url": "http://abs.twimg.com/images/themes/theme1/bg.png", "profile_sidebar_fill_color": "000000", "screen_name": "Adela_HerreraP", "id": 3015618088, "statuses_count": 10187, "friends_count": 1445, "default_profile_image": false, "id_str": "3015618088", "profile_banner_url": "https://pbs.twimg.com/profile_banners/3015618088/1538262698", "favourites_count": 48787, "profile_link_color": "981CEB", "profile_image_url": "http://pbs.twimg.com/profile_images/1040989001027645440/-5WlvhDq_normal.jpg", "followers_count": 481, "time_zone": null, "profile_use_background_image": true, "entities": {"description": {"urls": []}, "url": {"urls": [{"expanded_url": "http://todoslosescritorestienenunblog.wordpress.com", "indices": [0, 23], "display_url": "\u2026sescritorestienenunblog.wordpress.com", "url": "https://t.co/GcZF3QH4qn"}]}}, "profile_image_url_https": "https://pbs.twimg.com/profile_images/1040989001027645440/-5WlvhDq_normal.jpg", "url": "https://t.co/GcZF3QH4qn", "default_profile": false}, "place": null, "in_reply_to_status_id": null, "is_quote_status": false, "retweeted": false, "contributors": null, "in_reply_to_screen_name": null, "coordinates": null, "in_reply_to_user_id_str": null, "id": 622423786294390787, "truncated": false, "favorited": false, "retweet_count": 0, "entities": {"urls": [], "hashtags": [{"text": "Sarcasmo", "indices": [131, 140]}], "symbols": [], "user_mentions": []}, "favorite_count": 0, "id_str": "622423786294390787", "geo": null}