{"in_reply_to_user_id": 14102151, "in_reply_to_screen_name": "efrenvillarreal", "truncated": false, "place": null, "favorited": false, "user": {"time_zone": null, "url": null, "utc_offset": null, "profile_background_image_url_https": "https://abs.twimg.com/images/themes/theme14/bg.gif", "is_translator": false, "verified": false, "followers_count": 1553, "profile_background_tile": false, "screen_name": "marateran9", "profile_banner_url": "https://pbs.twimg.com/profile_banners/108705478/1507578523", "name": "La Brava", "geo_enabled": true, "profile_link_color": "1B95E0", "listed_count": 23, "profile_use_background_image": false, "profile_sidebar_border_color": "FFFFFF", "default_profile_image": false, "is_translation_enabled": false, "id_str": "108705478", "created_at": "Tue Jan 26 20:17:32 +0000 2010", "has_extended_profile": true, "contributors_enabled": false, "favourites_count": 4895, "profile_sidebar_fill_color": "FFFFFF", "following": false, "lang": "es", "entities": {"description": {"urls": []}}, "friends_count": 911, "profile_background_color": "FFFFFF", "description": "Sonorense de nacimiento,  cachanilla de crianza y coraz\u00f3n...Desmadrosa por convicci\u00f3n \u26be\ud83e\udd18\ud83d\udc71\ud83d\udc85 #NoCierto #Sicierto\nHILOMINATI \ud83e\uddf5\ud83d\udd96\nIG & Snapchat: marateran9", "default_profile": false, "profile_image_url_https": "https://pbs.twimg.com/profile_images/883411847163953152/6tADuh3T_normal.jpg", "id": 108705478, "protected": false, "notifications": false, "statuses_count": 100233, "location": "Mexicali, BC", "follow_request_sent": false, "profile_image_url": "http://pbs.twimg.com/profile_images/883411847163953152/6tADuh3T_normal.jpg", "profile_text_color": "2C2C2C", "translator_type": "none", "profile_background_image_url": "http://abs.twimg.com/images/themes/theme14/bg.gif"}, "id_str": "623190495414497280", "created_at": "Mon Jul 20 17:59:27 +0000 2015", "in_reply_to_status_id_str": "623187386491535360", "in_reply_to_user_id_str": "14102151", "lang": "es", "retweeted": false, "entities": {"hashtags": [{"indices": [26, 35], "text": "Sarcasmo"}, {"indices": [36, 58], "text": "CalmateSolDelUniverso"}], "urls": [], "user_mentions": [{"id": 14102151, "name": "Tet\u00e9n", "id_str": "14102151", "screen_name": "efrenvillarreal", "indices": [0, 16]}], "symbols": []}, "coordinates": null, "favorite_count": 0, "id": 623190495414497280, "is_quote_status": false, "retweet_count": 0, "geo": null, "text": "@efrenvillarreal Claro... #Sarcasmo #CalmateSolDelUniverso :p", "contributors": null, "source": "<a href=\"http://twitter.com\" rel=\"nofollow\">Twitter Web Client</a>", "in_reply_to_status_id": 623187386491535360}