{"text": "@ESPNCapitanes @joserra_espn @rafapuente_espn @LRZague @adelarosa_espn Siiii #suscribo le hacen falta mexicanos al futbol mexicano #Iron\u00eda", "in_reply_to_status_id_str": "631542290780061696", "source": "<a href=\"https://mobile.twitter.com\" rel=\"nofollow\">Twitter Lite</a>", "created_at": "Wed Aug 12 19:09:53 +0000 2015", "in_reply_to_user_id": 313161713, "lang": "es", "user": {"profile_text_color": "333333", "created_at": "Wed Jun 08 07:14:14 +0000 2011", "following": false, "profile_background_tile": false, "profile_sidebar_border_color": "C0DEED", "is_translator": false, "profile_background_image_url_https": "https://abs.twimg.com/images/themes/theme1/bg.png", "notifications": false, "location": "Monterrey, Nuevo Le\u00f3n", "lang": "es", "verified": false, "name": "Salvador Altamirano", "profile_background_color": "C0DEED", "description": "Heart of a Champion / Because We Can / I Love Rock & Roll baby", "geo_enabled": true, "is_translation_enabled": false, "protected": false, "listed_count": 4, "translator_type": "none", "contributors_enabled": false, "has_extended_profile": false, "follow_request_sent": false, "utc_offset": null, "profile_background_image_url": "http://abs.twimg.com/images/themes/theme1/bg.png", "profile_sidebar_fill_color": "DDEEF6", "screen_name": "Chavaroti48", "id": 313161713, "statuses_count": 9076, "friends_count": 953, "default_profile_image": false, "id_str": "313161713", "profile_banner_url": "https://pbs.twimg.com/profile_banners/313161713/1471416209", "favourites_count": 2844, "profile_link_color": "1DA1F2", "profile_image_url": "http://pbs.twimg.com/profile_images/788611544644980736/d2oe8k0p_normal.jpg", "followers_count": 316, "time_zone": null, "profile_use_background_image": true, "entities": {"description": {"urls": []}}, "profile_image_url_https": "https://pbs.twimg.com/profile_images/788611544644980736/d2oe8k0p_normal.jpg", "url": null, "default_profile": true}, "place": null, "in_reply_to_status_id": 631542290780061696, "is_quote_status": false, "retweeted": false, "contributors": null, "in_reply_to_screen_name": "Chavaroti48", "coordinates": null, "in_reply_to_user_id_str": "313161713", "id": 631543142492209154, "truncated": false, "favorited": false, "retweet_count": 0, "entities": {"urls": [], "hashtags": [{"text": "suscribo", "indices": [77, 86]}, {"text": "Iron\u00eda", "indices": [131, 138]}], "symbols": [], "user_mentions": [{"name": "LosCapitanes", "id": 103338935, "indices": [0, 14], "id_str": "103338935", "screen_name": "ESPNCapitanes"}, {"name": "Jos\u00e9 Ram\u00f3n Fern\u00e1ndez", "id": 111372842, "indices": [15, 28], "id_str": "111372842", "screen_name": "joserra_espn"}, {"name": "Rafael Puente", "id": 213400880, "indices": [29, 45], "id_str": "213400880", "screen_name": "rafapuente_espn"}, {"name": "Zague", "id": 3063093909, "indices": [46, 54], "id_str": "3063093909", "screen_name": "LRZague"}, {"name": "Alejandro de la Rosa", "id": 114584352, "indices": [55, 70], "id_str": "114584352", "screen_name": "adelarosa_espn"}]}, "favorite_count": 0, "id_str": "631543142492209154", "geo": null}